pjps/__init__.py
pjps/__main__.py
pjps/core.py
pjps/gui.py
pjps/locale.py
pjps/platform.py
pjps/tui.py
pjps-1.0.1.dist-info/METADATA
pjps-1.0.1.dist-info/WHEEL
pjps-1.0.1.dist-info/entry_points.txt
pjps-1.0.1.dist-info/top_level.txt
pjps-1.0.1.dist-info/RECORD
