Metadata-Version: 2.4
Name: pjps
Version: 1.0.1
Summary: A powerful process viewer with TUI and GUI - ps on steroids
Author-email: Paige Julianne Sullivan <paige@paigejulianne.com>
License-Expression: MIT
Project-URL: Homepage, https://github.com/paigejulianne/pjps
Project-URL: Repository, https://github.com/paigejulianne/pjps
Keywords: process,ps,htop,tui,gui,system,monitor
Classifier: Development Status :: 4 - Beta
Classifier: Environment :: Console :: Curses
Classifier: Environment :: X11 Applications :: GTK
Classifier: Intended Audience :: System Administrators
Classifier: Operating System :: POSIX :: Linux
Classifier: Programming Language :: Python :: 3
Classifier: Programming Language :: Python :: 3.8
Classifier: Programming Language :: Python :: 3.9
Classifier: Programming Language :: Python :: 3.10
Classifier: Programming Language :: Python :: 3.11
Classifier: Programming Language :: Python :: 3.12
Classifier: Topic :: System :: Monitoring
Classifier: Topic :: System :: Systems Administration
Requires-Python: >=3.8
Requires-Dist: psutil>=5.9.0
Requires-Dist: urwid>=2.1.0
Provides-Extra: test
Requires-Dist: pytest>=7.0.0; extra == "test"
Requires-Dist: pytest-cov>=4.0.0; extra == "test"
Provides-Extra: dev
Requires-Dist: pytest>=7.0.0; extra == "dev"
Requires-Dist: pytest-cov>=4.0.0; extra == "dev"
